bambuluc/__init__.py
bambuluc-1.3.0.dist-info/licenses/LICENSE
pyarmor_runtime_000000/__init__.py
pyarmor_runtime_000000/__pycache__/__init__.cpython-313.pyc
pyarmor_runtime_000000/darwin_x86_64/pyarmor_runtime.so
pyarmor_runtime_000000/linux_x86_64/pyarmor_runtime.so
pyarmor_runtime_000000/windows_x86_64/pyarmor_runtime.pyd
bambuluc-1.3.0.dist-info/METADATA
bambuluc-1.3.0.dist-info/WHEEL
bambuluc-1.3.0.dist-info/top_level.txt
bambuluc-1.3.0.dist-info/RECORD
