Metadata-Version: 2.4
Name: bambuluc
Version: 1.3.0
Summary: Control completo para impresoras Bambu Lab 
Author: Angel Luis Barbero Guerras
Project-URL: Homepage, https://github.com/AngelBarbero/bambuluc
Project-URL: Bug Reports, https://github.com/AngelBarbero/bambuluc/issues
Project-URL: Source, https://github.com/AngelBarbero/bambuluc
Project-URL: Documentation, https://github.com/AngelBarbero/bambuluc/blob/main/README.md
Keywords: bambu,3d printer,mqtt,ftp,automation,3mf,gcode
Classifier: Development Status :: 5 - Production/Stable
Classifier: Intended Audience :: Developers
Classifier: Intended Audience :: Manufacturing
Classifier: Topic :: Software Development :: Libraries :: Python Modules
Classifier: Topic :: System :: Hardware :: Hardware Drivers
Classifier: Topic :: Scientific/Engineering
Classifier: Programming Language :: Python :: 3
Classifier: Programming Language :: Python :: 3.7
Classifier: Programming Language :: Python :: 3.8
Classifier: Programming Language :: Python :: 3.9
Classifier: Programming Language :: Python :: 3.10
Classifier: Programming Language :: Python :: 3.11
Classifier: Programming Language :: Python :: 3.12
Classifier: Operating System :: OS Independent
Requires-Python: >=3.7
License-File: LICENSE
Requires-Dist: paho-mqtt>=1.6.0
Provides-Extra: dev
Requires-Dist: pytest>=6.0; extra == "dev"
Requires-Dist: pytest-asyncio>=0.18.0; extra == "dev"
Requires-Dist: black>=22.0; extra == "dev"
Requires-Dist: flake8>=4.0; extra == "dev"
Dynamic: license-file
